mongogrant/__init__.py
mongogrant/app.py
mongogrant/client.py
mongogrant/config.py
mongogrant/server.py
mongogrant/scripts/__init__.py
mongogrant/scripts/mgrant.py
mongogrant/tests/__init__.py
mongogrant/tests/test_app.py
mongogrant/tests/test_client.py
mongogrant/tests/test_config.py
mongogrant/tests/test_server.py
mongogrant/tests/utils.py
mongogrant-0.3.3.dist-info/LICENSE
mongogrant-0.3.3.dist-info/METADATA
mongogrant-0.3.3.dist-info/WHEEL
mongogrant-0.3.3.dist-info/entry_points.txt
mongogrant-0.3.3.dist-info/top_level.txt
mongogrant-0.3.3.dist-info/RECORD
