Metadata-Version: 2.1
Name: mongogrant
Version: 0.3.3
Summary: Generate and grant credentials for MongoDB databases
Home-page: https://github.com/materialsproject/mongogrant/
Author: MP Team
Author-email: feedback@materialsproject.org
License: modified BSD
Keywords: mongodb pymongo authentication authorization
Platform: UNKNOWN
Classifier: Development Status :: 3 - Alpha
Classifier: Programming Language :: Python :: 3
Classifier: Programming Language :: Python :: 3.6
Classifier: Intended Audience :: System Administrators
Classifier: Intended Audience :: Developers
Classifier: Topic :: Database
Classifier: Topic :: Database :: Database Engines/Servers
Classifier: Topic :: Database :: Front-Ends
Classifier: Topic :: System :: Systems Administration
Requires-Python: >=3
Requires-Dist: Click
Requires-Dist: pymongo (>=3.8)
Requires-Dist: Flask (>=1.0)
Requires-Dist: requests
